tiptoestep/__init__.py
tiptoestep/action.py
tiptoestep/agent.py
tiptoestep/env.py
tiptoestep/messenger.py
tiptoestep/proto.py
tiptoestep/service.py
tiptoestep/setting.py
tiptoestep/utils.py
tiptoestep-0.0.1a0.dist-info/METADATA
tiptoestep-0.0.1a0.dist-info/WHEEL
tiptoestep-0.0.1a0.dist-info/top_level.txt
tiptoestep-0.0.1a0.dist-info/RECORD
